qt_dev_helper/__init__.py
qt_dev_helper/__main__.py
qt_dev_helper/config.py
qt_dev_helper/qt_tools.py
qt_dev_helper/transpiler.py
qt_dev_helper/utils.py
qt_dev_helper/cli/__init__.py
qt_dev_helper/cli/_cli_docs.py
qt_dev_helper/cli/main_app.py
qt_dev_helper/cli/utils.py
qt_dev_helper/cli/commands/__init__.py
qt_dev_helper/cli/commands/build.py
qt_dev_helper/cli/commands/designer.py
qt_dev_helper-0.0.4.dist-info/LICENSE
qt_dev_helper-0.0.4.dist-info/METADATA
qt_dev_helper-0.0.4.dist-info/WHEEL
qt_dev_helper-0.0.4.dist-info/entry_points.txt
qt_dev_helper-0.0.4.dist-info/top_level.txt
qt_dev_helper-0.0.4.dist-info/RECORD
