Metadata-Version: 2.1
Name: qt-dev-helper
Version: 0.0.4
Summary: Tool to help developing Qt applications
Home-page: https://github.com/s-weigand/qt-dev-helper
Author: Sebastian Weigand
Author-email: s.weigand.phy@gmail.com
License: Apache Software License 2.0
Project-URL: Documentation, https://qt-dev-helper.readthedocs.io
Project-URL: Changelog, https://qt-dev-helper.readthedocs.io/en/latest/history.html
Project-URL: Source, https://github.com/s-weigand/qt-dev-helper
Project-URL: Tracker, https://github.com/s-weigand/qt-dev-helper/issues
Keywords: qt_dev_helper
Classifier: Development Status :: 2 - Pre-Alpha
Classifier: Intended Audience :: Developers
Classifier: License :: OSI Approved :: Apache Software License
Classifier: Natural Language :: English
Classifier: Programming Language :: Python :: 3
Classifier: Programming Language :: Python :: 3 :: Only
Classifier: Programming Language :: Python :: 3.8
Classifier: Programming Language :: Python :: 3.9
Classifier: Programming Language :: Python :: 3.10
Classifier: Programming Language :: Python :: 3.11
Requires-Python: >=3.8
License-File: LICENSE
Requires-Dist: pydantic (<2,>=1.9.0)
Requires-Dist: qtsass (>=0.3.1)
Requires-Dist: rich (>=12.0.0)
Requires-Dist: tomli (>=2.0.1)
Provides-Extra: cli
Requires-Dist: typer (>=0.4.0) ; extra == 'cli'
Provides-Extra: pyside6
Requires-Dist: PySide6-Essentials ; extra == 'pyside6'
